src/sequence_counter/seq_ctr.v
module seq_ctr (
    input wire ip, clk, rst,
    output reg opt
);

parameter [2:0]s0=3'b000, s1=3'b001, s2=3'b010, s3=3'b011, s4=3'b100;
reg [2:0] st,nt;

always @(posedge clk)
begin
    if(rst==0)
    st<= s0;
    else
    st<= nt;
end

always @(*)
begin
    case(st)
    s0:
    begin
        if(ip==1)
        nt = s1;
        else
        nt = s0;
    end
    s1:
    begin
        if(ip==0)
        nt = s2;
        else
        nt = s1;
    end
    s2:
    begin
        if(ip==1)
        nt = s3;
        else
        nt = s0;
    end
    s3:
    begin
        if(ip==1)
        nt = s4;
        else
        nt = s2;
    end
    s3:
    begin
        if(ip==0)
        nt = s2;
        else
        nt = s1;
    end
    default: nt = s0;
    endcase
end

 
always @(*)
begin
    case(st)
    s0: opt= 0;
    s1: opt= 0;
    s2: opt= 0;
    s3: opt= 0;
    s4: opt= 1;
    default: opt = 0;
    endcase
end

endmodule

src/sequence_counter/test_seq_ctr.v
module testbench;
    reg ip, clk, rst;
    wire opt;

    // Instantiate the DUT
    seq_ctr dut (
        .ip(ip),
        .clk(clk),
        .rst(rst),
        .opt(opt)
    );

    // Generate stimulus
    initial begin
        $dumpfile("test_seq_ctr.vcd"); // Specify the VCD file name
        $dumpvars(0, testbench); // Dump all variables in the testbench
        $monitor("At time %t: a = %b, b = %b, sum = %b, carry = %b", $time, ip, clk, rst, opt);
        clk = 0; rst = 0; ip=0;
        #10;
        rst = 1; ip=0;
        #10;
        ip=1;
        #10;
        ip=0;
        #10;
        ip=1;
        #10;
        ip=1;
        #10;
        ip=1;
        #10;
        $finish;
    end
    always #5 clk = ~clk;
endmodule

src/sequence_counter/test_seq_ctr.vcd
$date
	Thu Aug 01 21:11:43 2024
$end
$version
	Icarus Verilog
$end
$timescale
	1s
$end
$scope module testbench $end
$var wire 1 ! opt $end
$var reg 1 " clk $end
$var reg 1 # ip $end
$var reg 1 $ rst $end
$scope module dut $end
$var wire 1 " clk $end
$var wire 1 # ip $end
$var wire 1 $ rst $end
$var parameter 3 % s0 $end
$var parameter 3 & s1 $end
$var parameter 3 ' s2 $end
$var parameter 3 ( s3 $end
$var parameter 3 ) s4 $end
$var reg 3 * nt [2:0] $end
$var reg 1 ! opt $end
$var reg 3 + st [2:0] $end
$upscope $end
$upscope $end
$enddefinitions $end
$comment Show the parameter values. $end
$dumpall
b100 )
b11 (
b10 '
b1 &
b0 %
$end
#0
$dumpvars
bx +
b0 *
0$
0#
0"
x!
$end
#5
0!
b0 +
1"
#10
0"
1$
#15
1"
#20
b1 *
0"
1#
#25
b1 +
1"
#30
b10 *
0"
0#
#35
b0 *
b10 +
1"
#40
b11 *
0"
1#
#45
b100 *
b11 +
1"
#50
0"
#55
1!
b0 *
b100 +
1"
#60
0"
#65
0!
b1 *
b0 +
1"
