src/full_adder/full_adder.v
module full_adder (
    input wire a, b, cin,
    output wire sum, carry
);
    assign sum = a ^ b ^ cin;
    assign carry = a & b | a & cin | b & cin;
endmodule

tests/test_full_adder.v
module testbench;
    reg a, b, cin;
    wire sum, carry;

    // Instantiate the DUT
    full_adder dut (
        .a(a),
        .b(b),
        .cin(cin),
        .sum(sum),
        .carry(carry)
    );

    // Generate stimulus
    initial begin
        $dumpfile("build/full_adder.vcd"); // Specify the VCD file name
        $dumpvars(0, testbench); // Dump all variables in the testbench
        $monitor("At time %t: a = %b, b = %b, cin = %b, sum = %b, carry = %b", $time, a, b, cin, sum, carry);
        a = 0; b = 0; cin=0;
        #10;
        a = 0; b = 1; cin=0;
        #10;
        a = 1; b = 0; cin=0;
        #10;
        a = 1; b = 1; cin=0;
        #10;
        a = 0; b = 0; cin=1;
        #10;
        a = 0; b = 1; cin=1;
        #10;
        a = 1; b = 0; cin=1;
        #10;
        a = 1; b = 1; cin=1;
        #10;
        $finish;
    end
endmodule

full_adder/test_full_adder.vcd
$date
	Thu Aug 01 16:25:37 2024
$end
$version
	Icarus Verilog
$end
$timescale
	1s
$end
$scope module testbench $end
$var wire 1 ! sum $end
$var wire 1 " carry $end
$var reg 1 # a $end
$var reg 1 $ b $end
$var reg 1 % cin $end
$scope module dut $end
$var wire 1 # a $end
$var wire 1 $ b $end
$var wire 1 " carry $end
$var wire 1 % cin $end
$var wire 1 ! sum $end
$upscope $end
$upscope $end
$enddefinitions $end
$comment Show the parameter values. $end
$dumpall
$end
#0
$dumpvars
0%
0$
0#
0"
0!
$end
#10
1!
1$
#20
0$
1#
#30
1"
0!
1$
#40
0"
1!
1%
0$
0#
#50
0!
1"
1$
#60
0$
1#
#70
1!
1$
